lazy_b/__init__.py
lazy_b/cli.py
lazy_b/integrated_runner.py
lazy_b/main.py
lazy_b/py.typed
lazy_b/animations/__init__.py
lazy_b/animations/core.py
lazy_b/animations/interactive_menu.py
lazy_b/animations/repository.py
lazy_b/animations/types.py
lazy_b/animations/utils.py
lazy_b-0.3.2.data/data/animations/convertFramesToTxt.js
lazy_b-0.3.2.data/data/animations/frames.js
lazy_b-0.3.2.data/data/animations/dancing_stick_figure/001_frame.txt
lazy_b-0.3.2.data/data/animations/dancing_stick_figure/002_frame.txt
lazy_b-0.3.2.data/data/animations/dancing_stick_figure/003_frame.txt
lazy_b-0.3.2.data/data/animations/my_animation/001_happy.txt
lazy_b-0.3.2.data/data/animations/my_animation/002_surprised.txt
lazy_b-0.3.2.data/data/animations/my_animation/003_sleepy.txt
lazy_b-0.3.2.data/data/animations/never_gonna_give_you_up/frame_1.txt
lazy_b-0.3.2.data/data/animations/never_gonna_give_you_up/frame_10.txt
lazy_b-0.3.2.data/data/animations/never_gonna_give_you_up/frame_11.txt
lazy_b-0.3.2.data/data/animations/never_gonna_give_you_up/frame_12.txt
lazy_b-0.3.2.data/data/animations/never_gonna_give_you_up/frame_13.txt
lazy_b-0.3.2.data/data/animations/never_gonna_give_you_up/frame_14.txt
lazy_b-0.3.2.data/data/animations/never_gonna_give_you_up/frame_15.txt
lazy_b-0.3.2.data/data/animations/never_gonna_give_you_up/frame_16.txt
lazy_b-0.3.2.data/data/animations/never_gonna_give_you_up/frame_17.txt
lazy_b-0.3.2.data/data/animations/never_gonna_give_you_up/frame_18.txt
lazy_b-0.3.2.data/data/animations/never_gonna_give_you_up/frame_19.txt
lazy_b-0.3.2.data/data/animations/never_gonna_give_you_up/frame_2.txt
lazy_b-0.3.2.data/data/animations/never_gonna_give_you_up/frame_20.txt
lazy_b-0.3.2.data/data/animations/never_gonna_give_you_up/frame_21.txt
lazy_b-0.3.2.data/data/animations/never_gonna_give_you_up/frame_22.txt
lazy_b-0.3.2.data/data/animations/never_gonna_give_you_up/frame_23.txt
lazy_b-0.3.2.data/data/animations/never_gonna_give_you_up/frame_24.txt
lazy_b-0.3.2.dist-info/METADATA
lazy_b-0.3.2.dist-info/WHEEL
lazy_b-0.3.2.dist-info/entry_points.txt
lazy_b-0.3.2.dist-info/licenses/LICENSE
lazy_b-0.3.2.dist-info/RECORD
