Metadata-Version: 2.4
Name: lazy-b
Version: 0.3.2
Summary: Keep Slack/Teams active by simulating key presses at regular intervals
Project-URL: Homepage, https://github.com/Lanznx/lazy-b
Project-URL: Bug Tracker, https://github.com/Lanznx/lazy-b/issues
Project-URL: Documentation, https://github.com/Lanznx/lazy-b#readme
Project-URL: Source Code, https://github.com/Lanznx/lazy-b
Author-email: Brandon Lu <brandonlu0924@gmail.com>
License: MIT
License-File: LICENSE
Keywords: automation,away,inactive,keypress,simulate,slack,teams,utility
Classifier: Development Status :: 3 - Alpha
Classifier: Environment :: MacOS X
Classifier: Intended Audience :: Developers
Classifier: Intended Audience :: End Users/Desktop
Classifier: Intended Audience :: Information Technology
Classifier: Intended Audience :: System Administrators
Classifier: License :: OSI Approved :: MIT License
Classifier: Operating System :: MacOS :: MacOS X
Classifier: Operating System :: Microsoft :: Windows
Classifier: Operating System :: POSIX :: Linux
Classifier: Programming Language :: Python :: 3
Classifier: Programming Language :: Python :: 3.8
Classifier: Programming Language :: Python :: 3.9
Classifier: Programming Language :: Python :: 3.10
Classifier: Programming Language :: Python :: 3.11
Classifier: Topic :: Utilities
Requires-Python: >=3.8
Requires-Dist: pyautogui>=0.9.54
Provides-Extra: dev
Requires-Dist: black>=22.0.0; extra == 'dev'
Requires-Dist: build>=0.8.0; extra == 'dev'
Requires-Dist: mypy>=0.950; extra == 'dev'
Requires-Dist: pytest-cov>=3.0.0; extra == 'dev'
Requires-Dist: pytest>=7.0.0; extra == 'dev'
Requires-Dist: ruff>=0.0.200; extra == 'dev'
Requires-Dist: twine>=4.0.0; extra == 'dev'
Provides-Extra: macos
Requires-Dist: pyobjc-core>=7.0.0; extra == 'macos'
Requires-Dist: pyobjc-framework-cocoa>=7.0.0; extra == 'macos'
